rstk/__init__.py
rstk/cli.py
rstk/preprocessor.py
rstk/algo/__init__.py
rstk/algo/content_based/__init__.py
rstk/algo/content_based/knn.py
rstk-0.1.3.dist-info/LICENSE
rstk-0.1.3.dist-info/METADATA
rstk-0.1.3.dist-info/WHEEL
rstk-0.1.3.dist-info/entry_points.txt
rstk-0.1.3.dist-info/top_level.txt
rstk-0.1.3.dist-info/RECORD
