Metadata-Version: 2.1
Name: rstk
Version: 0.1.3
Summary: Lightweight recommender system toolkit
Home-page: https://github.com/rat-nick/rstk
Author: Nikola Ratinac
Author-email: nikola.ratinac@gmail.com
License: 3-clause BSD
License-File: LICENSE
Requires-Dist: click
Requires-Dist: pandas
Requires-Dist: numpy
Requires-Dist: scikit-learn
